{
    "objectid": "5",
    "SHAPE": "(-156.09374999999997, -89.89103875499995)",
    "globalid": "{006920B5-6D1D-491B-8F00-4606FEC59A85}",
    "start": "2025-09-15 14:50:39.000001",
    "nombre": "Calle 70 AV 3B bis Norte  ",
    "fecha_recolec": "2025-09-15 17:00:00",
    "via": "Calle 70 ",
    "municipio": "CALI",
    "inspector": "GRB",
    "n_secciones": "1",
    "abscisado": "N",
    "paso_cauce": "yes",
    "existe_variante": "no",
    "long_variante": "",
    "estado_variante": "",
    "num_luces": "1",
    "luz_menor_m": "",
    "luz_mayor_m": "",
    "longitud_total_m": "4.8",
    "ancho_tablero_m": "7.8",
    "ancho_separador_m": "",
    "ancho_anden_izq_m": "0.8",
    "ancho_anden_der_m": "0.8",
    "ancho_calzada_m": "6.2",
    "ancho_entrebordillos_m": "8.1",
    "altura_pilas_m": "",
    "altura_estribos_m": "1.75",
    "long_apoyo_pilas_m": "",
    "long_apoyo_estribos_m": "",
    "puente_terraplen": "no",
    "puente_cobertura": "",
    "esviajamiento_gra": "",
    "diseno_tipo1": "7",
    "tipo_transversal": "2",
    "tipo_longitudinal": "",
    "desc_tipo_trans1": "",
    "desc_tipo_long1": "",
    "material_principal": "2",
    "estado_super": "B",
    "general_sub_estructura": "",
    "tiene_super_sec": "no",
    "tipo_transversal_2": "",
    "tipo_longitudinal_2": "",
    "desc_tipo_trans": "",
    "desc_tipo_long": "",
    "material_secundaria": "",
    "estado_secu": "",
    "general_subes_secu": "",
    "tiene_estribos": "yes",
    "tipo_estribo": "0",
    "estribos_material": "3",
    "estribos_cimentacion": "",
    "estado_estribos": "",
    "obs_estribo": "",
    "tiene_pilas": "",
    "pilas_tipo": "",
    "pilas_forma": "",
    "pilas_material": "",
    "pilas_cimentacion": "",
    "obs_pilas": "",
    "tiene_baranda": "yes",
    "estado_baranda": "B",
    "obs_baranda": "",
    "tipo_superficie": "",
    "estado_superficie": "B",
    "obs_superficie": "Presenta un desgaste leve ",
    "tipo_junta": "1",
    "estado_junta": "B",
    "obs_junta": "",
    "tiene_senales": "",
    "tiene_senal_carga": "",
    "carga_max": "",
    "tiene_senal_vel": "",
    "vel_max": "",
    "tiene_otra_senal": "",
    "otra_senal": "",
    "tiene_apoyos_estribos": "yes",
    "apoyo_fijo_estribo": "0",
    "apoyo_movil_estribo": "",
    "estado_apoyo_sobre_est": "B",
    "obs_apoyo_estribos": "",
    "tiene_apoyos_pilas": "no",
    "apoyo_fijo_pilas": "",
    "apoyo_movil_pilas": "",
    "estado_apoyo_s_pila": "",
    "obs_apoyo_pila": "",
    "tiene_apoyos_vigas": "no",
    "apoyo_fijo_vigas": "",
    "apoyo_movil_vigas": "",
    "estado_apoyo_s_viga": "",
    "obs_apoyo_viga": "",
    "calif_sup": "0",
    "mant_sup": "no",
    "inspesp_sup": "no",
    "tipo_sup": "",
    "obs_sup": "",
    "tiene_juntas": "no",
    "calif_juntas": "",
    "mant_juntas": "",
    "inspesp_juntas": "",
    "tipo_juntas": "",
    "obs_juntas": "",
    "tiene_andenes": "yes",
    "anden_bordillo": "anden,bordillo",
    "calif_anden": "0",
    "mant_anden": "no",
    "inspesp_anden": "no",
    "tipo_anden": "",
    "obs_anden": "",
    "calif_bordillo": "0",
    "mant_bordillo": "no",
    "inspesp_bordillo": "no",
    "tipo_bordillo": "",
    "obs_bordillo": "",
    "tiene_barandas": "yes",
    "calif_barandas": "0",
    "mant_barandas": "no",
    "inspesp_barandas": "no",
    "tipo_barandas": "",
    "obs_barandas": "",
    "tiene_conos": "no",
    "conos_talud": "",
    "calif_cono": "",
    "mant_cono": "",
    "inspesp_cono": "",
    "tipo_cono": "",
    "obs_cono": "",
    "calif_talud": "",
    "mant_talud": "",
    "inspesp_talud": "",
    "tipo_talud": "",
    "obs_talud": "",
    "tiene_aletas": "no",
    "calif_aletas": "",
    "mant_aletas": "",
    "inspesp_aletas": "",
    "tipo_aletas": "",
    "obs_aletas": "",
    "calif_estribos": "0",
    "mant_estribos": "no",
    "inspesp_estribos": "no",
    "tipo_estribos": "",
    "obs_estribos": "",
    "calif_pilas": "",
    "mant_pilas": "",
    "inspesp_pilas": "",
    "tipo_pilas": "",
    "tiene_apoyos": "no",
    "calif_apoyos": "",
    "mant_apoyos": "",
    "inspesp_apoyos": "",
    "tipo_apoyos": "",
    "obs_apoyos": "",
    "tiene_losa": "no",
    "calif_losa": "",
    "mant_losa": "",
    "inspesp_losa": "",
    "tipo_losa": "",
    "obs_losa": "",
    "tiene_vigas": "no",
    "v_l_d": "",
    "calif_viga": "",
    "mant_viga": "",
    "inspesp_viga": "",
    "tipo_viga": "",
    "obs_viga": "",
    "calif_larguero": "",
    "mant_larguero": "",
    "inspesp_larguero": "",
    "tipo_larguero": "",
    "obs_larguero": "",
    "calif_diafragma": "",
    "mant_diafragma": "",
    "inspesp_diafragma": "",
    "tipo_diafragma": "",
    "obs_diafragma": "",
    "tiene_arco": "no",
    "calif_arco": "",
    "mant_arco": "",
    "inspesp_arco": "",
    "tipo_arco": "",
    "obs_arco": "",
    "tiene_cables": "no",
    "c_t_p_m": "",
    "calif_cables": "",
    "mant_cables": "",
    "inspesp_cables": "",
    "tipo_cables": "",
    "obs_cables": "",
    "calif_pendolones": "",
    "mant_pendolones": "",
    "inspesp_pendolones": "",
    "tipo_pendolones": "",
    "obs_pendolones": "",
    "calif_torres": "",
    "mant_torres": "",
    "inspesp_torres": "",
    "tipo_torres": "",
    "obs_torres": "",
    "calif_macizos": "",
    "mant_macizos": "",
    "inspesp_macizos": "",
    "tipo_macizos": "",
    "obs_macizos": "",
    "tiene_armadura": "no",
    "calif_armadura": "",
    "mant_armadura": "",
    "inspesp_armadura": "",
    "tipo_armadura": "",
    "obs_armadura": "",
    "tiene_cauce": "yes",
    "calif_cauce": "0",
    "mant_cauce": "no",
    "inspesp_cauce": "no",
    "tipo_cauce": "",
    "obs_cauce": "",
    "tiene_otros": "no",
    "calif_otros": "",
    "mant_otros": "",
    "inspesp_otros": "",
    "tipo_otros": "",
    "obs_otros": "",
    "calif_general": "0",
    "mant_general": "no",
    "inspesp_general": "no",
    "obs_general": "",
    "CreationDate": "2025-09-15 15:13:32",
    "Creator": "",
    "EditDate": "2025-11-22 18:14:35",
    "Editor": "NESTO",
    "tipo_puente_gen": "ponton",
    "estado_pilas": "",
    "X": -156.09374999999997,
    "Y": -89.89103875499995,
    "EPSG": 4326,
    "fotos": {
        "anden": [
            {
                "ruta": "anden/{006920b5-6d1d-491b-8f00-4606fec59a85}_foto_anden_20250915101101.jpg",
                "drive": "https://drive.google.com/file/d/1iOonx0ICb-zRb1k072r0ZEfs28KaPM8L/view?usp=drivesdk"
            }
        ],
        "bordillo": [
            {
                "ruta": "bordillo/{006920b5-6d1d-491b-8f00-4606fec59a85}_foto_bordillo_20250915101124.jpg",
                "drive": "https://drive.google.com/file/d/10vWR30Mp18AxmwnVD9nuWQhRC9jR0J-u/view?usp=drivesdk"
            }
        ],
        "general": [
            {
                "ruta": "gen/{006920b5-6d1d-491b-8f00-4606fec59a85}_foto_general_20250915101323.jpg",
                "drive": "https://drive.google.com/file/d/1BK-qAne16GLCjkddACb3X0S3ItOeYn3_/view?usp=drivesdk"
            }
        ]
    }
}