{
    "objectid": "17",
    "SHAPE": "(-76.52200762199999, 3.4941959050000264)",
    "globalid": "{7A89DDBA-F27C-46EC-8937-3BE008904100}",
    "start": "2025-09-16 13:34:38",
    "nombre": "Calle 70 con 1 norte sur ",
    "fecha_recolec": "2025-09-16 17:00:00",
    "via": "Carrera 1 ",
    "municipio": "CALI",
    "inspector": "GRB ",
    "n_secciones": "1",
    "abscisado": "S",
    "paso_cauce": "no",
    "existe_variante": "no",
    "long_variante": "",
    "estado_variante": "",
    "num_luces": "4",
    "luz_menor_m": "25.0",
    "luz_mayor_m": "26.0",
    "longitud_total_m": "",
    "ancho_tablero_m": "11.0",
    "ancho_separador_m": "",
    "ancho_anden_izq_m": "",
    "ancho_anden_der_m": "",
    "ancho_calzada_m": "",
    "ancho_entrebordillos_m": "",
    "altura_pilas_m": "",
    "altura_estribos_m": "",
    "long_apoyo_pilas_m": "",
    "long_apoyo_estribos_m": "",
    "puente_terraplen": "yes",
    "puente_cobertura": "",
    "esviajamiento_gra": "",
    "diseno_tipo1": "0",
    "tipo_transversal": "1",
    "tipo_longitudinal": "2",
    "desc_tipo_trans1": "",
    "desc_tipo_long1": "",
    "material_principal": "4",
    "estado_super": "R",
    "general_sub_estructura": "Losa presenta desgaste y corrosión en aceros ",
    "tiene_super_sec": "no",
    "tipo_transversal_2": "",
    "tipo_longitudinal_2": "",
    "desc_tipo_trans": "",
    "desc_tipo_long": "",
    "material_secundaria": "",
    "estado_secu": "",
    "general_subes_secu": "",
    "tiene_estribos": "yes",
    "tipo_estribo": "5",
    "estribos_material": "3",
    "estribos_cimentacion": "",
    "estado_estribos": "B",
    "obs_estribo": "",
    "tiene_pilas": "yes",
    "pilas_tipo": "3",
    "pilas_forma": "3",
    "pilas_material": "4",
    "pilas_cimentacion": "",
    "obs_pilas": "",
    "tiene_baranda": "yes",
    "estado_baranda": "B",
    "obs_baranda": "",
    "tipo_superficie": "1",
    "estado_superficie": "B",
    "obs_superficie": "",
    "tipo_junta": "1",
    "estado_junta": "B",
    "obs_junta": "",
    "tiene_senales": "no",
    "tiene_senal_carga": "",
    "carga_max": "",
    "tiene_senal_vel": "",
    "vel_max": "",
    "tiene_otra_senal": "",
    "otra_senal": "",
    "tiene_apoyos_estribos": "",
    "apoyo_fijo_estribo": "",
    "apoyo_movil_estribo": "",
    "estado_apoyo_sobre_est": "",
    "obs_apoyo_estribos": "",
    "tiene_apoyos_pilas": "",
    "apoyo_fijo_pilas": "",
    "apoyo_movil_pilas": "",
    "estado_apoyo_s_pila": "",
    "obs_apoyo_pila": "",
    "tiene_apoyos_vigas": "yes",
    "apoyo_fijo_vigas": "3",
    "apoyo_movil_vigas": "",
    "estado_apoyo_s_viga": "B",
    "obs_apoyo_viga": "",
    "calif_sup": "",
    "mant_sup": "no",
    "inspesp_sup": "no",
    "tipo_sup": "",
    "obs_sup": "",
    "tiene_juntas": "",
    "calif_juntas": "",
    "mant_juntas": "",
    "inspesp_juntas": "",
    "tipo_juntas": "",
    "obs_juntas": "",
    "tiene_andenes": "yes",
    "anden_bordillo": "anden,bordillo",
    "calif_anden": "0",
    "mant_anden": "no",
    "inspesp_anden": "no",
    "tipo_anden": "",
    "obs_anden": "",
    "calif_bordillo": "0",
    "mant_bordillo": "no",
    "inspesp_bordillo": "no",
    "tipo_bordillo": "",
    "obs_bordillo": "",
    "tiene_barandas": "yes",
    "calif_barandas": "0",
    "mant_barandas": "no",
    "inspesp_barandas": "no",
    "tipo_barandas": "",
    "obs_barandas": "",
    "tiene_conos": "no",
    "conos_talud": "",
    "calif_cono": "",
    "mant_cono": "",
    "inspesp_cono": "",
    "tipo_cono": "",
    "obs_cono": "",
    "calif_talud": "",
    "mant_talud": "",
    "inspesp_talud": "",
    "tipo_talud": "",
    "obs_talud": "",
    "tiene_aletas": "no",
    "calif_aletas": "",
    "mant_aletas": "",
    "inspesp_aletas": "",
    "tipo_aletas": "",
    "obs_aletas": "",
    "calif_estribos": "0",
    "mant_estribos": "no",
    "inspesp_estribos": "no",
    "tipo_estribos": "",
    "obs_estribos": "",
    "calif_pilas": "0",
    "mant_pilas": "no",
    "inspesp_pilas": "no",
    "tipo_pilas": "",
    "tiene_apoyos": "yes",
    "calif_apoyos": "0",
    "mant_apoyos": "no",
    "inspesp_apoyos": "no",
    "tipo_apoyos": "",
    "obs_apoyos": "",
    "tiene_losa": "yes",
    "calif_losa": "0",
    "mant_losa": "no",
    "inspesp_losa": "no",
    "tipo_losa": "",
    "obs_losa": "",
    "tiene_vigas": "yes",
    "v_l_d": "viga,larguero",
    "calif_viga": "0",
    "mant_viga": "no",
    "inspesp_viga": "no",
    "tipo_viga": "",
    "obs_viga": "",
    "calif_larguero": "0",
    "mant_larguero": "no",
    "inspesp_larguero": "no",
    "tipo_larguero": "",
    "obs_larguero": "",
    "calif_diafragma": "",
    "mant_diafragma": "",
    "inspesp_diafragma": "",
    "tipo_diafragma": "",
    "obs_diafragma": "",
    "tiene_arco": "no",
    "calif_arco": "",
    "mant_arco": "",
    "inspesp_arco": "",
    "tipo_arco": "",
    "obs_arco": "",
    "tiene_cables": "no",
    "c_t_p_m": "",
    "calif_cables": "",
    "mant_cables": "",
    "inspesp_cables": "",
    "tipo_cables": "",
    "obs_cables": "",
    "calif_pendolones": "",
    "mant_pendolones": "",
    "inspesp_pendolones": "",
    "tipo_pendolones": "",
    "obs_pendolones": "",
    "calif_torres": "",
    "mant_torres": "",
    "inspesp_torres": "",
    "tipo_torres": "",
    "obs_torres": "",
    "calif_macizos": "",
    "mant_macizos": "",
    "inspesp_macizos": "",
    "tipo_macizos": "",
    "obs_macizos": "",
    "tiene_armadura": "no",
    "calif_armadura": "",
    "mant_armadura": "",
    "inspesp_armadura": "",
    "tipo_armadura": "",
    "obs_armadura": "",
    "tiene_cauce": "no",
    "calif_cauce": "",
    "mant_cauce": "",
    "inspesp_cauce": "",
    "tipo_cauce": "",
    "obs_cauce": "",
    "tiene_otros": "no",
    "calif_otros": "",
    "mant_otros": "",
    "inspesp_otros": "",
    "tipo_otros": "",
    "obs_otros": "",
    "calif_general": "0",
    "mant_general": "no",
    "inspesp_general": "no",
    "obs_general": "",
    "CreationDate": "2025-09-16 14:28:32",
    "Creator": "",
    "EditDate": "2025-11-22 18:14:35",
    "Editor": "NESTO",
    "tipo_puente_gen": "mix",
    "estado_pilas": "",
    "X": -76.52200762199999,
    "Y": 3.4941959050000264,
    "EPSG": 4326,
    "fotos": {
        "anden": [
            {
                "ruta": "anden/{7a89ddba-f27c-46ec-8937-3be008904100}_IMG_6389.jpeg",
                "drive": "https://drive.google.com/file/d/1W2rmxaTdaGWnEMedIThpzaFijvag2GjL/view?usp=drivesdk"
            }
        ],
        "general": [
            {
                "ruta": "gen/{7a89ddba-f27c-46ec-8937-3be008904100}_IMG_6387.jpeg",
                "drive": "https://drive.google.com/file/d/1lOFIIw4k45lcDVeZ85Acoog7aRJO3fTq/view?usp=drivesdk"
            }
        ]
    }
}